_simpy/__init__.py
_simpy/_compat.py
_simpy/_version.py
_simpy/core.py
_simpy/events.py
_simpy/exceptions.py
_simpy/rt.py
_simpy/util.py
_simpy/resources/__init__.py
_simpy/resources/base.py
_simpy/resources/container.py
_simpy/resources/resource.py
_simpy/resources/store.py
marmot/__init__.py
marmot/_core.py
marmot/_exceptions.py
marmot/_version.py
marmot/agent.py
marmot/environment.py
marmot/object.py
marmot_agents-0.2.5.dist-info/LICENSE
marmot_agents-0.2.5.dist-info/METADATA
marmot_agents-0.2.5.dist-info/WHEEL
marmot_agents-0.2.5.dist-info/top_level.txt
marmot_agents-0.2.5.dist-info/RECORD
