Metadata-Version: 2.1
Name: marmot-agents
Version: 0.2.5
Summary: Agent based processs modeling.
Home-page: https://github.com/JakeNunemaker/marmot
Author: Jake Nunemaker
Author-email: jake.d.nunemaker@gmail.com
License: BSD-3
Platform: UNKNOWN
Classifier: Development Status :: 4 - Beta
Classifier: Programming Language :: Python :: 3.7
Requires-Dist: numpy
